.flake8
LICENSE
MANIFEST.in
README.md
law.cfg.example
requirements.txt
setup.py
bin/law
bin/law2
bin/law3
law/__init__.py
law/__main__.py
law/__version__.py
law/config.py
law/decorator.py
law/logger.py
law/notification.py
law/parameter.py
law/parser.py
law/patches.py
law/polyfills.sh
law/util.py
law.egg-info/PKG-INFO
law.egg-info/SOURCES.txt
law.egg-info/dependency_links.txt
law.egg-info/entry_points.txt
law.egg-info/not-zip-safe
law.egg-info/requires.txt
law.egg-info/top_level.txt
law/cli/__init__.py
law/cli/cli.py
law/cli/completion.py
law/cli/completion.sh
law/cli/config.py
law/cli/index.py
law/cli/law
law/cli/law2
law/cli/law3
law/cli/location.py
law/cli/luigid.py
law/cli/quickstart.py
law/cli/run.py
law/cli/software.py
law/contrib/__init__.py
law/contrib/arc/__init__.py
law/contrib/arc/config.py
law/contrib/arc/decorator.py
law/contrib/arc/job.py
law/contrib/arc/util.py
law/contrib/arc/workflow.py
law/contrib/awkward/__init__.py
law/contrib/awkward/formatter.py
law/contrib/cms/__init__.py
law/contrib/cms/config.py
law/contrib/cms/console_scripts.json
law/contrib/cms/job.py
law/contrib/cms/sandbox.py
law/contrib/cms/tasks.py
law/contrib/cms/util.py
law/contrib/cms/workflow.py
law/contrib/cms/bin/apmon
law/contrib/cms/crab/PSet.py
law/contrib/cms/crab/crab_wrapper.sh
law/contrib/cms/scripts/__init__.py
law/contrib/cms/scripts/bundle_cmssw.sh
law/contrib/cms/scripts/cmsdashb_apmon_hooks.sh
law/contrib/cms/scripts/cmssw_checksum.sh
law/contrib/cms/scripts/delegate_myproxy.py
law/contrib/cms/scripts/setup_cmssw.sh
law/contrib/cms/scripts/setup_gfal_plugins.sh
law/contrib/coffea/__init__.py
law/contrib/coffea/formatter.py
law/contrib/docker/__init__.py
law/contrib/docker/config.py
law/contrib/docker/sandbox.py
law/contrib/dropbox/__init__.py
law/contrib/dropbox/config.py
law/contrib/dropbox/target.py
law/contrib/gfal/__init__.py
law/contrib/gfal/config.py
law/contrib/gfal/target.py
law/contrib/git/__init__.py
law/contrib/git/scripts/bundle_repository.sh
law/contrib/git/scripts/repository_checksum.sh
law/contrib/glite/__init__.py
law/contrib/glite/config.py
law/contrib/glite/job.py
law/contrib/glite/workflow.py
law/contrib/hdf5/__init__.py
