Metadata-Version: 2.1
Name: law
Version: 0.1.20
Summary: Build large-scale task workflows using luigi, remote job submission, remote targets, and environment
Home-page: https://github.com/riga/law
Author: Marcel Rieger
Author-email: github.riga@icloud.com
License: BSD-3-Clause
Keywords: luigi workflow pipeline remote gfal submission cluster grid condor lsf glite arc sandboxing docker singularity
Platform: UNKNOWN
Classifier: Programming Language :: Python
Classifier: Programming Language :: Python :: 2
Classifier: Programming Language :: Python :: 2.7
Classifier: Programming Language :: Python :: 3
Classifier: Programming Language :: Python :: 3.6
Classifier: Programming Language :: Python :: 3.7
Classifier: Programming Language :: Python :: 3.8
Classifier: Programming Language :: Python :: 3.9
Classifier: Programming Language :: Python :: 3.10
Classifier: Programming Language :: Python :: 3.11
Classifier: Development Status :: 4 - Beta
Classifier: Operating System :: OS Independent
Classifier: License :: OSI Approved :: BSD License
Classifier: Intended Audience :: Developers
Classifier: Intended Audience :: Science/Research
Classifier: Intended Audience :: Information Technology
Classifier: Topic :: System :: Monitoring
Requires-Python: >=2.7, !=3.0.*, !=3.1.*, !=3.2.*, !=3.3.*, !=3.4.*, !=3.5.*, <4
License-File: LICENSE
